panel_web_llm/__init__.py
panel_web_llm/cli.py
panel_web_llm/main.py
panel_web_llm/models.py
panel_web_llm/py.typed
panel_web_llm/settings.py
panel_web_llm/webllm.js
panel_web_llm-0.0.2.dist-info/METADATA
panel_web_llm-0.0.2.dist-info/WHEEL
panel_web_llm-0.0.2.dist-info/entry_points.txt
panel_web_llm-0.0.2.dist-info/licenses/LICENSE.txt
panel_web_llm-0.0.2.dist-info/RECORD
