Metadata-Version: 2.4
Name: panel-web-llm
Version: 0.0.2
Summary: Extends HoloViz Panel with an interface that wraps a client-side LLM.
Project-URL: Homepage, https://github.com/panel-extensions/panel-web-llm
Project-URL: Source, https://github.com/panel-extensions/panel-web-llm
Author-email: Andrew <a.holoviz.dev@gmail.com>
Maintainer-email: Andrew <a.holoviz.dev@gmail.com>
License: BSD
License-File: LICENSE.txt
Classifier: Development Status :: 5 - Production/Stable
Classifier: Intended Audience :: Developers
Classifier: Intended Audience :: Science/Research
Classifier: License :: OSI Approved :: BSD License
Classifier: Natural Language :: English
Classifier: Operating System :: OS Independent
Classifier: Programming Language :: Python :: 3
Classifier: Programming Language :: Python :: 3.10
Classifier: Programming Language :: Python :: 3.11
Classifier: Programming Language :: Python :: 3.12
Classifier: Programming Language :: Python :: 3.13
Classifier: Topic :: Scientific/Engineering
Classifier: Topic :: Software Development :: Libraries
Requires-Python: >=3.10
Requires-Dist: packaging
Requires-Dist: panel>=1.5.0
Provides-Extra: dev
Requires-Dist: mkdocs; extra == 'dev'
Requires-Dist: mkdocs-material; extra == 'dev'
Requires-Dist: mkdocs-pycafe; extra == 'dev'
Requires-Dist: mkdocstrings[python]; extra == 'dev'
Requires-Dist: pre-commit; extra == 'dev'
Requires-Dist: pytest; extra == 'dev'
Requires-Dist: pytest-asyncio; extra == 'dev'
Requires-Dist: pytest-rerunfailures; extra == 'dev'
Requires-Dist: pytest-xdist; extra == 'dev'
Requires-Dist: watchfiles; extra == 'dev'
Provides-Extra: mypy
Requires-Dist: mypy; extra == 'mypy'
Requires-Dist: types-requests; extra == 'mypy'
Requires-Dist: typing-extensions; extra == 'mypy'
